mergetiff/__init__.py
mergetiff/cli.py
mergetiff/lib.py
mergetiff-0.0.19.dist-info/DESCRIPTION.rst
mergetiff-0.0.19.dist-info/METADATA
mergetiff-0.0.19.dist-info/RECORD
mergetiff-0.0.19.dist-info/WHEEL
mergetiff-0.0.19.dist-info/entry_points.txt
mergetiff-0.0.19.dist-info/metadata.json
mergetiff-0.0.19.dist-info/top_level.txt
mergetiff-0.0.19.dist-info/zip-safe
