Metadata-Version: 2.0
Name: mergetiff
Version: 0.0.19
Summary: Library and command-line tool to merge GeoTiff files using GDAL
Home-page: http://github.com/adamrehn/mergetiff
Author: Adam Rehn
Author-email: adam@adamrehn.com
License: MIT
Keywords: gdal geotiff
Platform: UNKNOWN
Classifier: License :: OSI Approved :: MIT License
Classifier: Programming Language :: Python :: 2.7
Classifier: Programming Language :: Python :: 3.4
Classifier: Programming Language :: Python :: 3.5
Classifier: Programming Language :: Python :: 3.6
Classifier: Environment :: Console
Requires-Dist: GDAL (>=2)
Requires-Dist: numpy
Requires-Dist: psutil
